Metadata-Version: 1.1
Name: cinq-auditor-vpc-flowlogs
Version: 1.0.2
Summary: VPC Flow Log auditor
Home-page: https://github.com/RiotGames/cinq-auditor-vpc-flowlogs/
Author: Riot Games Security
Author-email: security@riotgames.com
License: License :: OSI Approved :: Apache Software License
Keywords: cloud security
Platform: UNKNOWN
Classifier: Development Status :: 4 - Beta
Classifier: Intended Audience :: System Administrators
Classifier: Intended Audience :: Information Technology
Classifier: License :: OSI Approved :: Apache Software License
Classifier: Programming Language :: Python :: 3.5
Classifier: Programming Language :: Python :: 3.6
Classifier: Framework :: Flask
Classifier: Framework :: Sphinx
Classifier: Operating System :: MacOS :: MacOS X
Classifier: Operating System :: POSIX :: Linux
Classifier: Operating System :: Unix
Classifier: Environment :: Console
Classifier: Natural Language :: English
Classifier: Topic :: Security
Classifier: Topic :: Utilities
